README.md
setup.py
mecab_ko_dic/__init__.py
mecab_ko_dic/ipadic.py
mecab_ko_dic.egg-info/PKG-INFO
mecab_ko_dic.egg-info/SOURCES.txt
mecab_ko_dic.egg-info/dependency_links.txt
mecab_ko_dic.egg-info/top_level.txt
mecab_ko_dic/dicdir/COPYING
mecab_ko_dic/dicdir/char.bin
mecab_ko_dic/dicdir/dicrc
mecab_ko_dic/dicdir/left-id.def
mecab_ko_dic/dicdir/matrix.bin
mecab_ko_dic/dicdir/mecabrc
mecab_ko_dic/dicdir/model.bin
mecab_ko_dic/dicdir/pos-id.def
mecab_ko_dic/dicdir/rewrite.def
mecab_ko_dic/dicdir/right-id.def
mecab_ko_dic/dicdir/sys.dic
mecab_ko_dic/dicdir/unk.dic
mecab_ko_dic/dicdir/version