Metadata-Version: 2.1
Name: mecab-ko-dic
Version: 1.0.0
Summary: mecab-ko-dic packaged for Python
Home-page: https://github.com/LuminosoInsight/mecab-ko-dic
Author: Robyn Speer
Author-email: rspeer@luminoso.com
License: UNKNOWN
Platform: UNKNOWN
Classifier: Programming Language :: Python :: 3
Classifier: Operating System :: OS Independent
Classifier: Natural Language :: Korean
